{
  "lastUpdated": "2026-04-21T06:03:17.162Z",
  "events": [
    {
      "date": "2026-03-18",
      "time": "6:15",
      "ampm": "AM",
      "title": "Spring Yoga with Ranunculus",
      "location": "Gilcrease Orchard",
      "description": "Start your morning with a refreshing yoga flow surrounded by blooming ranunculus fields.",
      "category": "Fitness & wellness",
      "color": "#D95D39",
      "bookingUrl": "thegilcreaseorchard.org",
      "contact": "@gilcreaseorchard",
      "price": 28
    },
    {
      "date": "2026-03-20",
      "time": "17:15",
      "ampm": "PM",
      "title": "Sunset Spring Yoga",
      "location": "Gilcrease Orchard",
      "description": "An evening yoga session at the orchard designed to help you unwind during the golden hour.",
      "category": "Fitness & wellness",
      "color": "#D95D39",
      "bookingUrl": "thegilcreaseorchard.org",
      "contact": "@gilcreaseorchard",
      "price": 28
    },
    {
      "date": "2026-03-21",
      "time": "11:00",
      "ampm": "AM",
      "title": "Dear Brwn Mama",
      "location": "",
      "description": "",
      "category": "Family Friendly",
      "color": "#4A4E69",
      "bookingUrl": "https://www.dearbrwnmama.com/event-details/bunny-bash",
      "contact": "@Dearbrwnmama",
      "price": 12
    },
    {
      "date": "2026-03-24",
      "time": "17:00",
      "ampm": "PM",
      "title": "Rooftop Candlelit Pilates",
      "location": "Keller Cactus Hills",
      "description": "A serene evening session of candlelit Pilates and meditation followed by wellness shots and juices.",
      "category": "Fitness & wellness",
      "color": "#D95D39",
      "bookingUrl": "pi-lattes.com",
      "contact": "@pilatteslv",
      "price": ""
    },
    {
      "date": "2026-03-24",
      "time": "18:00",
      "ampm": "PM",
      "title": "Scrap & Yap",
      "location": "Henderson, NV",
      "description": "",
      "category": "Arts & Culture",
      "color": "#4A4E69",
      "bookingUrl": "https://partiful.com/e/MIdLm98usiziy7yayQ2k",
      "contact": "@cozycollectivelv",
      "price": ""
    },
    {
      "date": "2026-03-25",
      "time": "6:15",
      "ampm": "AM",
      "title": "Sunrise Spring Yoga",
      "location": "Gilcrease Orchard",
      "description": "A sunrise yoga practice located in the heart of the historic orchard's flower fields.",
      "category": "Fitness & wellness",
      "color": "#D95D39",
      "bookingUrl": "thegilcreaseorchard.org",
      "contact": "@gilcreaseorchard",
      "price": 28
    },
    {
      "date": "2026-03-27",
      "time": "6:15",
      "ampm": "AM",
      "title": "Sunrise Spring Yoga",
      "location": "Gilcrease Orchard",
      "description": "An early morning yoga flow surrounded by blooming ranunculus flowers in the historic orchard.",
      "category": "Fitness & wellness",
      "color": "#D95D39",
      "bookingUrl": "thegilcreaseorchard.org",
      "contact": "@gilcreaseorchard",
      "price": 28
    },
    {
      "date": "2026-03-27",
      "time": "17:15",
      "ampm": "PM",
      "title": "Sunset Spring Yoga",
      "location": "Gilcrease Orchard",
      "description": "Unwind with a sunset yoga practice set against the beautiful backdrop of the spring orchard.",
      "category": "Fitness & wellness",
      "color": "#D95D39",
      "bookingUrl": "thegilcreaseorchard.org",
      "contact": "@gilcreaseorchard",
      "price": 28
    },
    {
      "date": "2026-03-27",
      "time": "18:02",
      "ampm": "PM",
      "title": "Swing Dance Night at The Coffee Note",
      "location": "The Coffee Note",
      "description": "Ready to shake off those weekday blues and step into something effortlessly cool? This Friday brings the perfect blend of vintage charm and modern energy with live jazz, beginner-friendly dance lessons, and that intimate coffee house atmosphere that makes every night feel like a scene from your favorite film.",
      "category": "Music & Entertainment",
      "color": "#7B3E19",
      "bookingUrl": "",
      "contact": "@thecoffeenotelv",
      "price": "$15-18"
    },
    {
      "date": "2026-03-28",
      "time": "18:15",
      "ampm": "PM",
      "title": "Sunset Spring Yoga",
      "location": "Gilcrease Orchard",
      "description": "A golden hour yoga session at the orchard perfect for unwinding among the spring flower fields.",
      "category": "Fitness & wellness",
      "color": "#D95D39",
      "bookingUrl": "thegilcreaseorchard.org",
      "contact": "@gilcreaseorchard",
      "price": 28
    },
    {
      "date": "2026-03-28",
      "time": "11:00",
      "ampm": "AM",
      "title": "Make & Mingle: DIY Coaster Workshop",
      "location": "",
      "description": "",
      "category": "Creative Workshop",
      "color": "#4A4E69",
      "bookingUrl": "https://partiful.com/e/K7ES9hxeTAMbGI0gTzO4",
      "contact": "@cozycollectivelv",
      "price": 12
    },
    {
      "date": "2026-03-28",
      "time": "14:00",
      "ampm": "PM",
      "title": "Mats and Margaritas: DIY Doormat Workshop",
      "location": "Board & Brush Creative Studio - Centennial Hills",
      "description": "Picture this: you, your favorite people, and the perfect blend of creativity and cocktails as you craft a custom doormat that'll make every guest jealous before they even step inside. This intimate workshop combines hands-on DIY magic with that celebratory margarita energy we all need more of in our lives.",
      "category": "Creative Workshop",
      "color": "#4A4E69",
      "bookingUrl": "https://boardandbrush.com/centennialhills/events/mats-and-margaritas-diy-doormat-workshop-03-28-2026-2pm-330pm/?utm_source=ig&utm_medium=social&utm_content=link_in_bio&fbclid=PAdGRleAQtaLFleHRuA2FlbQExAHNydGMGYXBwX2lkDzEyNDAyNDU3NDI4NzQxNAABp6HpQYWjFIZFlRSP7c96L0JV1yXKPO0F_Ljhs66TyxIeBjgDkftbdyuTmx8k_aem_28nuRkwrMmNLQh5_scB0WA",
      "contact": "@boardandbrushcentennialhills",
      "price": 45
    },
    {
      "date": "2026-03-28",
      "time": "14:00",
      "ampm": "PM",
      "title": "Mats and Margaritas: DIY Doormat Workshop",
      "location": "Board and Brush - Centennial Hills",
      "description": "This perfectly crafted afternoon combines creative expression with social sipping as you design a custom doormat that'll make your guests smile before they even knock. It's the kind of hands-on experience that feeds your soul while giving you something gorgeous to take home – plus, the margaritas don't hurt either.",
      "category": "Arts & Culture",
      "color": "#4A4E69",
      "bookingUrl": "https://boardandbrush.com/centennialhills/events/mats-and-margaritas-diy-doormat-workshop-03-28-2026-2pm-330pm/?utm_source=ig&utm_medium=social&utm_content=link_in_bio&fbclid=PAdGRleAQtaLFleHRuA2FlbQExAHNydGMGYXBwX2lkDzEyNDAyNDU3NDI4NzQxNAABp6HpQYWjFIZFlRSP7c96L0JV1yXKPO0F_Ljhs66TyxIeBjgDkftbdyuTmx8k_aem_28nuRkwrMmNLQh5_scB0WA",
      "contact": "@boardandbrushcentennialhills",
      "price": 40
    },
    {
      "date": "2026-03-29",
      "time": "12:00",
      "ampm": "PM",
      "title": "Pilates Pool Party",
      "location": "Ariva",
      "description": "Get Fit event with cardio splash, pool deck Pilates, and food.",
      "category": "Fitness & Social",
      "color": "#4A4E69",
      "bookingUrl": "sweatpals.com",
      "contact": "@getfitlasvegas",
      "price": "Free"
    },
    {
      "date": "2026-03-29",
      "time": "18:00",
      "ampm": "PM",
      "title": "Yoga in the Park",
      "location": "Bruce Trent Park",
      "description": "Join Solely Committed Co. for a evening session of yoga in the park. Each session is community offerings and donations are accepted. Please reach out to @breathewithraven for any additional information.",
      "category": "Wellness & Fitness",
      "color": "#D95D39",
      "bookingUrl": "",
      "contact": "@breathewithraven",
      "price": "Free"
    },
    {
      "date": "2026-03-29",
      "time": "8:00",
      "ampm": "AM",
      "title": "Mindset x Movement: Run Into The New Season",
      "location": "Better Days Coffee - Flamingo",
      "description": "Join a curated running collective for an invigorating morning that perfectly balances mindful movement with the fresh energy of a new season. This isn't just another group run—it's your invitation to connect with like-minded souls while setting intentions that will carry you beautifully into what's next.",
      "category": "Wellness & Fitness",
      "color": "#D95D39",
      "bookingUrl": "https://dailydopamine.co/products/mindset-x-movement-run-into-the-new-season?variant=53976529535260",
      "contact": "@gracerunclub",
      "price": 40
    },
    {
      "date": "2026-04-04",
      "time": "13:00",
      "ampm": "PM",
      "title": "Girls Paint at the Park",
      "location": "NW Las Vegas",
      "description": "Elevated outdoor paint experience with mocktails and a floral bar.",
      "category": "Arts & Culture",
      "color": "#4A4E69",
      "bookingUrl": "girlsnightinpaintandsip.com",
      "contact": "@girlsnightinpaintandsip",
      "price": 25
    },
    {
      "date": "2026-04-04",
      "time": "10:00",
      "ampm": "AM",
      "title": "Sock Bunny Workshop",
      "location": "",
      "description": "",
      "category": "Creative Workshop",
      "color": "#4A4E69",
      "bookingUrl": "https://partiful.com/e/AfcOwayPwQXMmAZLBu9T",
      "contact": "@cozycollectivelv",
      "price": 15
    },
    {
      "date": "2026-04-04",
      "time": "10:15",
      "ampm": "AM",
      "title": "Black People Hike LV: State of the Trail Civic Unity Hike",
      "location": "Lone Mountain",
      "description": "Join this meaningful community gathering that combines the healing power of nature with important civic dialogue as you explore the scenic trails of Lone Mountain. It's a beautiful opportunity to connect with like-minded hikers while engaging in thoughtful conversations about our community's future in one of Vegas's most stunning outdoor settings.",
      "category": "Wellness & Fitness",
      "color": "#D95D39",
      "bookingUrl": "https://allevents.in/las-vegas/80007248079795?ref=sharer",
      "contact": "@blackpeoplehikelv",
      "price": "Free"
    },
    {
      "date": "2026-04-04",
      "time": "18:00",
      "ampm": "PM",
      "title": "The Cozmic Lounge: Y2K Night",
      "location": "Bad Beat Brewing",
      "description": "Step back into the iconic Y2K era with Cozmic Mocktail Club, where metallic fits and nostalgic beats create the perfect throwback vibe that only Vegas can deliver. This is your chance to experience the electric energy of millennium nostalgia in one of the city's most stylish underground venues.",
      "category": "Food & Drink",
      "color": "#7B3E19",
      "bookingUrl": "https://www.eventbrite.com/e/the-cozmic-lounge-y2k-night-tickets-1985645351699?utm-medium=discovery&utm-campaign=social&utm-content=attendeeshare&utm-source=up&utm-term=user-profile&aff=ebdsshcopyurl",
      "contact": "@cozmicmocktailclub",
      "price": 28
    },
    {
      "date": "2026-04-04",
      "time": "12:00",
      "ampm": "PM",
      "title": "Saturdays Are For the Girls Workout",
      "location": "Fury Co.",
      "description": "You know that feeling when you want to get your sweat on but also catch up with your crew without the awkward small talk of a regular gym class? This is for the woman who values her Saturday morning ritual but craves something more intentional than another solo gum session. Think high-energy vibes, actual connections, and the kind of workout that leaves you feeling like you conquered more than just your fitness goals.",
      "category": "Wellness & Fitness",
      "color": "#D95D39",
      "bookingUrl": "https://www.eventbrite.com/e/saturdays-are-for-the-girls-registration-1985667844977?utm-medium=discovery&utm-campaign=social&utm-content=attendeeshare&utm-source=up&utm-term=user-profile&aff=ebdsshcopyurl",
      "contact": "@she.clublv",
      "price": 35
    },
    {
      "date": "2026-04-05",
      "time": "18:00",
      "ampm": "PM",
      "title": "Yoga In the Park",
      "location": "Sunset Park",
      "description": "Join Solely Committed Co. for a evening session of yoga in the park. Each session is community offerings and donations are accepted. Please reach out to @breathewithraven for any additional information.",
      "category": "Wellness & Fitness",
      "color": "#D95D39",
      "bookingUrl": "",
      "contact": "@breathewithraven",
      "price": "Free"
    },
    {
      "date": "2026-04-05",
      "time": "10:00",
      "ampm": "AM",
      "title": "Spring Fling Pilates Social",
      "location": "Ferguson's Downtown",
      "description": "Spring is calling for a fresh fitness moment, and this Pilates social is exactly the kind of elevated wellness experience that discerning Las Vegas locals know makes all the difference. Picture yourself flowing through intentional movement with like-minded souls who understand that the best connections happen when you're investing in yourself.",
      "category": "Wellness & Fitness",
      "color": "#D95D39",
      "bookingUrl": "https://www.eventbrite.com/e/spring-fling-pilates-social-tickets-1985591029219?utm-medium=discovery&utm-campaign=social&utm-content=attendeeshare&utm-source=up&utm-term=user-profile&aff=ebdsshcopyurl",
      "contact": "@nabcurated",
      "price": 35
    },
    {
      "date": "2026-04-08",
      "time": "18:30",
      "ampm": "PM",
      "title": "Clay & Chisme",
      "location": "The Pottery Shop",
      "description": "Join us for the perfect blend of creativity and conversation at The Pottery Shop, where you'll get your hands dirty crafting beautiful ceramics while sharing stories and secrets with fellow creatives. It's the kind of evening where meaningful connections are made over messy clay and flowing chisme — exactly what your soul needs right now.",
      "category": "Creative Workshop",
      "color": "#4A4E69",
      "bookingUrl": "https://posh.vip/e/clay-chisme-?utm_source=ig&utm_medium=social&utm_content=link_in_bio&fbclid=PAdGRleAQpsGFleHRuA2FlbQIxMQBzcnRjBmFwcF9pZA8xMjQwMjQ1NzQyODc0MTQAAaefpRW1-c9FjEGLoeqdC4Ge2MU5VDhEqDj4vmLOaWZ9_aPBvwBTErg1h5sULQ_aem_1z3DCpLSiAq6wFzIj8ff-w",
      "contact": "@amigamovement",
      "price": 10
    },
    {
      "date": "2026-04-10",
      "time": "19:00",
      "ampm": "PM",
      "title": "Plant Bingo",
      "location": "Spilled Milk Store",
      "description": "Get ready for the most delightfully unexpected evening where your love for greenery meets the thrill of bingo in Vegas' coziest plant haven. This isn't your grandmother's bingo night – it's where plant parents and curious souls gather for an evening of friendly competition, botanical prizes, and the kind of authentic connections that make this city feel like home.",
      "category": "Social",
      "color": "#D95D39",
      "bookingUrl": "https://www.spilledmilkstore.com/product/plant-bingo-april-2026/ZYTCDCZTESKOT5IAWZCKHDTB?cp=true&sa=true&sbp=false&q=false&utm_source=ig&utm_medium=social&utm_content=link_in_bio&fbclid=PAdGRleAQprldleHRuA2FlbQIxMQBzcnRjBmFwcF9pZA8xMjQwMjQ1NzQyODc0MTQAAaf2CaLSSW5eqUwhkgfsG_5L-cvmZGGBzmQN3ZQ89i_zvkYNCWSd9eRzhja2vA_aem_T_TDo6kWHNKypj2ympYkTQ",
      "contact": "",
      "price": 40
    },
    {
      "date": "2026-04-10",
      "time": "18:30",
      "ampm": "PM",
      "title": "F The Bar: Mixology Workshop - Saddle Up Sip",
      "location": "Ferguson's Downtown",
      "description": "If you're the type who knows the difference between good vodka and great vodka and thinks most cocktail classes are too basic, this mixology workshop at Ferguson's is calling your name. You'll learn to craft elevated ranch-inspired cocktails that actually belong in your repertoire, not just your Instagram feed, all while connecting with other women who appreciate the art of a perfectly balanced drink.",
      "category": "Food & Drink",
      "color": "#7B3E19",
      "bookingUrl": "https://www.eventbrite.com/e/f-the-bar-mixology-workshop-saddle-up-sip-featuring-weber-ranch-tickets-1984942212591?utm-medium=discovery&utm-campaign=social&utm-content=attendeeshare&utm-source=up&utm-term=user-profile&aff=ebdsshcopyurl",
      "contact": "@fergusonsdowntown",
      "price": 45
    },
    {
      "date": "2026-04-10",
      "time": "18:30",
      "ampm": "PM",
      "title": "R&B Yoga + Meditation Class",
      "location": "3110 E Sunset Rd unit d Las Vegas, NV",
      "description": "This soulful R&B-inspired yoga and meditation experience by Qui 2 Balance is exactly what you need to sink into rhythm and breathe into balance this Friday evening. You'll flow through gentle movements synced to smooth R&B beats, practice restorative breathwork, and close with grounding meditation in an atmosphere of pure compassion and ease.",
      "category": "Wellness & Fitness",
      "color": "#D95D39",
      "bookingUrl": "https://www.eventbrite.com/e/rb-yoga-meditation-class-tickets-1986598292972?aff=oddtdtcreator&utm_source=ig&utm_medium=social&utm_content=link_in_bio&fbclid=PAZnRzaAREtORleHRuA2FlbQIxMQBzcnRjBmFwcF9pZA8xMjQwMjQ1NzQyODc0MTQAAad6bjr8VC9uANgeLxolwuau5ojKxoY-eCSxcLrNuPzI6AUCzxCH6nV9AFMntA_aem_gpwNv59w1rH2mVhmhU_14Q",
      "contact": "@qui2balance",
      "price": 13
    },
    {
      "date": "2026-04-11",
      "time": "11:30",
      "ampm": "AM",
      "title": "Black Girl Mixer: Camera Confidence",
      "location": "",
      "description": "",
      "category": "Social",
      "color": "#D95D39",
      "bookingUrl": "https://www.blackgirlmixer.com/",
      "contact": "@blackgirlmixer",
      "price": 50
    },
    {
      "date": "2026-04-11",
      "time": "11:00",
      "ampm": "AM",
      "title": "Saturno Pilates",
      "location": "Electric Mushroom",
      "description": "This isn't your typical studio session—it's a transformative Pilates experience set against the eclectic backdrop of Electric Mushroom, where wellness meets Vegas' creative underground. Trust us when we say this fusion of mindful movement and artistic atmosphere will leave you feeling both centered and inspired in ways you never expected.",
      "category": "Wellness & Fitness",
      "color": "#D95D39",
      "bookingUrl": "https://posh.vip/e/saturno-pilates-1?utm_source=ig&utm_medium=social&utm_content=link_in_bio&fbclid=PAdGRleAQtaT5leHRuA2FlbQIxMQBzcnRjBmFwcF9pZA8xMjQwMjQ1NzQyODc0MTQAAaeD_DxIx1UsbGKhcelwM4uFNIJAfAERlgwKIizawCVuYHpgl97tXoFk_2gzpA_aem_Y0ss98NfEMZ0MJzDexFNdA",
      "contact": "@masquepilates",
      "price": 35
    },
    {
      "date": "2026-04-11",
      "time": "17:00",
      "ampm": "PM",
      "title": "The Zodiac Series: Aries Pilates",
      "location": "BLVD Rooftop",
      "description": "Channel your fiery Aries energy with an invigorating Pilates session designed specifically for the bold and determined ram, set against the stunning backdrop of BLVD Rooftop. This celestial-inspired workout combines the intensity Aries craves with mindful movement that will leave you feeling as powerful and radiant as the stars themselves.",
      "category": "Wellness & Fitness",
      "color": "#D95D39",
      "bookingUrl": "https://thezodiacserieslv.com/#d933a79e-c726-40ea-a644-0143cb72bf31",
      "contact": "@emberxfrost",
      "price": "$55-396"
    },
    {
      "date": "2026-04-11",
      "time": "17:00",
      "ampm": "PM",
      "title": "Body Butter Workshop - Better Days",
      "location": "Better Days Cafe(Spring Valley)",
      "description": "Learn the art of creating luxurious, nourishing body butters in this hands-on workshop that's perfect for anyone looking to elevate their self-care routine with handcrafted wellness. This intimate experience will have you blending natural ingredients like a pro while connecting with fellow wellness enthusiasts who share your passion for clean beauty and mindful living.",
      "category": "Creative Workshop",
      "color": "#4A4E69",
      "bookingUrl": "https://bodybutterbybrianna.com/shop/p/body-butter-workshop-better-days?utm_source=ig&utm_medium=social&utm_content=link_in_bio&fbclid=PAdGRleAQyFiRleHRuA2FlbQIxMQBzcnRjBmFwcF9pZA8xMjQwMjQ1NzQyODc0MTQAAacY9HwkVuzXMP9XObIk-l3r_t11YLUNkKWeGt_uwm_-RlvttsIfW04Xnq5bRQ_aem_sJDatxGKWFnf-ZHuQM3dOQ",
      "contact": "@bodybutterbybrianna",
      "price": 50
    },
    {
      "date": "2026-04-11",
      "time": "9:00",
      "ampm": "AM",
      "title": "Romanticize Your Pilates",
      "location": "Keller Cactus Hills",
      "description": "This dreamy Pilates experience transforms your usual workout into something utterly enchanting, blending mindful movement with an atmosphere that feels like pure self-care luxury. Trust me, this is the kind of session that leaves you feeling both beautifully stretched and completely renewed – exactly what your spring wellness routine has been missing.",
      "category": "Wellness & Fitness",
      "color": "#D95D39",
      "bookingUrl": "https://www.pilateswithfatou.com/event-details/romanticize-your-pilates?utm_source=ig&utm_medium=social&utm_content=link_in_bio&fbclid=PAdGRleAQ2bmFleHRuA2FlbQIxMQBzcnRjBmFwcF9pZA8xMjQwMjQ1NzQyODc0MTQAAaftTnlBVhsL_ho85uRAyp2VGP2UdEYiutVuub9M884SBobkIng_X8QEmwEZXg_aem_rfofjjudiFBlZt97wxnr9Q",
      "contact": "@cafecitoychisme",
      "price": "$40-50"
    },
    {
      "date": "2026-04-11",
      "time": "11:00",
      "ampm": "AM",
      "title": "The Art of Cake",
      "location": "Uncommons",
      "description": "Picture this: a gathering where fellow cake enthusiasts come together to share their most treasured recipes and creations in the cozy, design-forward space that is Uncommons. It's the kind of delightfully unexpected afternoon where you'll discover your new favorite bakery secret, swap stories behind family recipes, and leave with both a satisfied sweet tooth and genuine new connections.",
      "category": "Food & Drink",
      "color": "#7B3E19",
      "bookingUrl": "https://uncommons.com/event/the-art-of-cake/",
      "contact": "@uncommonslv",
      "price": "Free"
    },
    {
      "date": "2026-04-11",
      "time": "7:30",
      "ampm": "AM",
      "title": "PopStroke Las Vegas X Move With Madi",
      "location": "PopStroke",
      "description": "Picture this: a perfect Vegas morning where you'll flow through an energizing workout with the incredible Madi, then unwind with mini golf and mimosas at the most Instagram-worthy spot in town. This is that rare combination of wellness and play that leaves you feeling both accomplished and completely refreshed – trust me, you'll want to clear your Saturday for this one.",
      "category": "Wellness & Fitness",
      "color": "#D95D39",
      "bookingUrl": "https://www.eventbrite.com/e/popstroke-las-vegas-x-move-with-madi-tickets-1985867121017?aff=eprofsaved",
      "contact": "@girlswalkvegas",
      "price": 30
    },
    {
      "date": "2026-04-11",
      "time": "11:00",
      "ampm": "AM",
      "title": "WISE Las Vegas Headshot & Professional Development Workshop",
      "location": "Ariva Luxury Residences",
      "description": "At this event, you'll walk away with professional headshots that actually capture your personality alongside career development strategies from women who've built real influence in this city. The intimate setting at Ariva means you're networking with intention rather than working a room full of business cards you'll never remember.",
      "category": "Networking",
      "color": "#22223B",
      "bookingUrl": "https://tr.ee/jBgVam0T5q",
      "contact": "@wiselv",
      "price": "$15-40"
    },
    {
      "date": "2026-04-12",
      "time": "18:00",
      "ampm": "PM",
      "title": "Yoga In the Park",
      "location": "Lone Mountain Park",
      "description": "Join Solely Committed Co. for a evening session of yoga in the park. Each session is community offerings and donations are accepted. Please reach out to @breathewithraven for any additional information.",
      "category": "Wellness & Fitness",
      "color": "#D95D39",
      "bookingUrl": "",
      "contact": "@breathewithraven",
      "price": "Free"
    },
    {
      "date": "2026-04-12",
      "time": "18:00",
      "ampm": "PM",
      "title": "Rooftop Soundbath & Yoga",
      "location": "3850 W Nevso Dr",
      "description": "Picture yourself flowing through gentle yoga poses as the sun sets over the Vegas skyline, then melting into pure bliss during a healing soundbath under the stars. This rooftop sanctuary experience combines movement, meditation, and those magical desert views that make you feel like you've discovered the city's best-kept wellness secret.",
      "category": "Wellness & Fitness",
      "color": "#D95D39",
      "bookingUrl": "https://checkout.square.site/merchant/ML2Q9RFG8F6VS/checkout/3MBICCJOFUAQPIVB2FNI5B5G?utm_source=ig&utm_medium=social&utm_content=link_in_bio&fbclid=PAdGRleAQtauJleHRuA2FlbQIxMQBzcnRjBmFwcF9pZA8xMjQwMjQ1NzQyODc0MTQAAadKgpwPaH7HPqf3nfbN7tMAXLrZAdp5bz4Bok9yKrPPFI-4nki6AoZRiR7uLw_aem_r9iq8uBxqYyMNdwMSPKrjQ",
      "contact": "@rootednflo",
      "price": 35
    },
    {
      "date": "2026-04-12",
      "time": "17:00",
      "ampm": "PM",
      "title": "Spring Fling Bachata Class & Social",
      "location": "Audio Bar",
      "description": "Have you been interested in learning a few moves to spice up your bachata? This event is perfect balace of instruction and application. No registration or cover needed. Drink specials are available from 5-6pm.",
      "category": "Social",
      "color": "#D95D39",
      "bookingUrl": "",
      "contact": "@bachataloungelv",
      "price": "Free"
    },
    {
      "date": "2026-04-12",
      "time": "18:00",
      "ampm": "PM",
      "title": "Rooftop: Soundbath & Yoga",
      "location": "3850 W Nevso Dr, Las Vegas",
      "description": "Escape the Vegas hustle with this perfectly curated rooftop experience that combines rejuvenating soundbath healing with sunset yoga flows - it's the kind of elevated wellness moment that makes you feel like you've discovered the city's best-kept secret. Trust me, this is where the mindful Vegas crowd gathers to reset and recharge while taking in those stunning desert views that remind you why this city is pure magic.",
      "category": "Wellness & Fitness",
      "color": "#D95D39",
      "bookingUrl": "https://www.eventbrite.com/e/rooftop-soundbath-and-yoga-event-tickets-1985674580122?utm-medium=discovery&utm-campaign=social&utm-content=attendeeshare&utm-source=up&utm-term=user-profile&aff=ebdsshcopyurl",
      "contact": "@rootednflo",
      "price": 40
    },
    {
      "date": "2026-04-12",
      "time": "12:00",
      "ampm": "PM",
      "title": "You Deserve Your Flowers Pilates for Healthcare Workers",
      "location": "Sunset Park",
      "description": "The morning air at Sunset Park carries a different kind of energy when it's filled with the quiet strength of those who spend their days caring for others, finally taking an hour to breathe deeply and stretch toward the desert sky. There's something profoundly moving about watching scrubs-clad heroes flow through sun salutations together, the distant hum of the city serving as a gentle reminder that they've stepped away from the chaos to honor themselves in this sacred pocket of green space.",
      "category": "Wellness & Fitness",
      "color": "#D95D39",
      "bookingUrl": "https://www.eventbrite.com/e/you-deserve-your-flowers-pilates-event-tickets-1983643687668?utm-medium=discovery&utm-campaign=social&utm-content=attendeeshare&utm-source=up&utm-term=user-profile&aff=ebdsshcopyurl",
      "contact": "@healthcarepilatessocial",
      "price": 25
    },
    {
      "date": "2026-04-12",
      "time": "7:30",
      "ampm": "AM",
      "title": "Morning Hike & Yoga in the Park",
      "location": "Exploration Peak Park",
      "description": "Start your weekend with intention at this perfectly curated morning hike and yoga experience in one of Vegas's most scenic spots - it's the kind of mindful adventure that locals treasure but visitors rarely discover. This is your chance to connect with like-minded souls while stretching both your body and your perspective of what wellness looks like in the desert.",
      "category": "Wellness & Fitness",
      "color": "#D95D39",
      "bookingUrl": "https://www.eventbrite.com/e/yogasix-mountains-edge-morning-hike-yoga-in-the-park-tickets-1986386858566?utm_experiment=test_share_listing&aff=ebdsshios&sg=fbc00c6ec24b6ac9e86aca2204aea8688cb330d98f3dd10d596bb29f75630f148d7bf246a7e11e89a0fa35b3e63b2df5f3aff5ac86c92f1310d4feec96343ab9d0fc0996f67313ba61de15ebf4",
      "contact": "@yogasix_mountainsedge",
      "price": "Free"
    },
    {
      "date": "2026-04-16",
      "time": "19:00",
      "ampm": "PM",
      "title": "Strings By the Sunset",
      "location": "Ferguson's Downtown",
      "description": "Picture this: an intimate evening where classical strings meet golden hour magic at Ferguson's Downtown, creating the kind of atmospheric moment that feels both sophisticated and soul-stirring. This is exactly the type of curated musical experience where you'll find yourself completely transported, surrounded by fellow culture enthusiasts who appreciate the finer moments in life.",
      "category": "Music & Entertainment",
      "color": "#7B3E19",
      "bookingUrl": "https://www.eventbrite.com/e/strings-by-the-sunset-tickets-1986048952881?utm-medium=discovery&utm-campaign=social&utm-content=attendeeshare&utm-source=up&utm-term=user-profile&aff=ebdsshcopyurl",
      "contact": "@fergusonsdowntown",
      "price": 25
    },
    {
      "date": "2026-04-18",
      "time": "",
      "ampm": "PM",
      "title": "Restore & Replenish Retreat",
      "location": "Self Elevate Studios",
      "description": "A full women's wellness retreat focused on reconnecting with self.",
      "category": "Fitness & Wellness",
      "color": "#D95D39",
      "bookingUrl": "girlspaintinsipandpaint.com",
      "contact": "@girlsnightinpaintandsip",
      "price": 100
    },
    {
      "date": "2026-04-18",
      "time": "17:00",
      "ampm": "PM",
      "title": "Sistas Y Hermanas Black & Brown Unity Hike",
      "location": "Hoover Dam Trail",
      "description": "Join this powerful celebration of Black and Brown sisterhood as we connect with nature and each other on the scenic Hoover Dam Trail, where breathtaking views meet meaningful conversations. It's the kind of soul-nourishing experience that reminds you why community and wellness go hand in hand—plus you'll discover one of Nevada's most stunning hiking spots through the eyes of incredible women.",
      "category": "Wellness & Fitness",
      "color": "#D95D39",
      "bookingUrl": "https://allevents.in/boulder-city/80001802354596?ref=sharer",
      "contact": "@blackpeoplehikelv",
      "price": "Free"
    },
    {
      "date": "2026-04-18",
      "time": "7:30",
      "ampm": "AM",
      "title": "Skye Canyon Pickleball Social",
      "location": "Skye Canyon Park",
      "description": "Whether you're curious about the fastest-growing sport in America or ready to compete, this community gathering offers the perfect introduction to pickleball with free clinics, novice and intermediate tournaments, plus food trucks to fuel the fun. It's that rare event where you can learn something new, break a sweat, and connect with fellow Las Vegans all in one beautiful morning at the park.",
      "category": "Wellness & Fitness",
      "color": "#D95D39",
      "bookingUrl": "",
      "contact": "",
      "price": "$0-10"
    },
    {
      "date": "2026-04-18",
      "time": "9:00",
      "ampm": "AM",
      "title": "Pool-Lates: Pilates at Hideout Pool",
      "location": "Golden Nugget Pool",
      "description": "Picture this: you're flowing through your favorite Pilates moves while floating on water, surrounded by the luxe vibes of Golden Nugget's stunning pool deck. It's the kind of workout that makes you feel like you've discovered the ultimate wellness secret – equal parts challenging and utterly rejuvenating.",
      "category": "Wellness & Fitness",
      "color": "#D95D39",
      "bookingUrl": "https://na.spatime.com/gnlv9101/4799809/activity/activity-view/59575211?fbclid=PAVERFWAQ2dCZleHRuA2FlbQIxMABzcnRjBmFwcF9pZA8xMjQwMjQ1NzQyODc0MTQAAadFnScYfGFPMfEuZdVZuJLKsfxrC9f95Mvs-jy8TV7h6R3EM_s5AvEonGyVJw_aem_ZtTNM6Qc0CcptbLRDRuJVQ",
      "contact": "@yogaforlifelv",
      "price": 35
    },
    {
      "date": "2026-04-18",
      "time": "7:00",
      "ampm": "AM",
      "title": "Beginner Yoga in the Park with Hustle & Yoga Flow",
      "location": "Hollywood Park",
      "description": "There's something magical about flowing through gentle poses under the open sky, and this beginner-friendly session with Hustle & Yoga Flow is the perfect way to ease into your wellness journey while soaking up Hollywood Park's serene atmosphere. Trust me, you'll leave feeling both grounded and energized, plus you'll discover that yoga outdoors hits completely differently than any studio class ever could.",
      "category": "Wellness & Fitness",
      "color": "#D95D39",
      "bookingUrl": "https://checkout.square.site/merchant/MLTJAW1BP1J1M/checkout/VP2QFSDZWFLTZARHJJAPDUOB?fbclid=IwdGRjcAQ3cYZleHRuA2FlbQIxMQBzcnRjBmFwcF9pZAo2NjI4NTY4Mzc5AAEeETeYDdpBLoxLtKYIOvmAwzf-2Gwt9feGq450NJvU-5FB0IRRGhYT52VZVBY_aem_qWRHOml1jxb31nysybyfRA",
      "contact": "@hustleyogaflow",
      "price": 10
    },
    {
      "date": "2026-04-18",
      "time": "10:00",
      "ampm": "AM",
      "title": "Breath & Beats: Yoga With a DJ",
      "location": "Ferguson's Downtown",
      "description": "Most yoga classes stick to predictable playlists, but this one features a live DJ reading the room and mixing beats that actually sync with your flow transitions. At just $10, it's the kind of accessible luxury that makes you wonder why more studios don't elevate the experience this thoughtfully.",
      "category": "Wellness & Fitness",
      "color": "#D95D39",
      "bookingUrl": "https://www.eventbrite.com/e/breath-beats-yoga-with-live-dj-at-fergusons-downtown-tickets-1985315120970?aff=eprofsaved",
      "contact": "@beksandrew",
      "price": 10
    },
    {
      "date": "2026-04-18",
      "time": "12:00",
      "ampm": "PM",
      "title": "Formation Haus Soft Opening with Pilates Activations",
      "location": "Formation Haus",
      "description": "This isn't just another studio launch party with mimosas and Instagram backdrops—Formation Haus is debuting with actual Pilates classes woven throughout their soft opening, letting you experience their teaching style and equipment quality before committing to a membership. At $50, you're getting first access to sample what could become your new movement sanctuary, plus the chance to secure founding member rates if their approach resonates with how you want to move your body.",
      "category": "Wellness & Fitness",
      "color": "#D95D39",
      "bookingUrl": "https://www.eventbrite.com/e/formation-haus-soft-opening-tickets-1985778267253?utm-medium=discovery&utm-campaign=social&utm-content=attendeeshare&utm-source=up&utm-term=user-profile&aff=ebdsshcopyurl",
      "contact": "@formationhaus",
      "price": 50
    },
    {
      "date": "2026-04-18",
      "time": "16:00",
      "ampm": "PM",
      "title": "Project P4: Pickleball, Pilates, and Pool",
      "location": "Plaza Hotel",
      "description": "The Plaza's rooftop transforms into a sun-soaked wellness playground where the satisfying pop of pickleball paddles mingles with the splash of poolside workouts and the focused breathing of mat-based flows. There's an infectious energy here that feels distinctly Vegas – part resort luxury, part community sweat session – where you'll find yourself genuinely surprised by how much fun fitness can be when it's wrapped in good music, city views, and the kind of day party vibe that makes you forget you're technically exercising.",
      "category": "Wellness & Fitness",
      "color": "#D95D39",
      "bookingUrl": "https://sweatpals.com/event/project-p4-pickleball-pilates-pool/2026-04-18?sourceCollectionPosition=3&sourceCollection=new-events&sourcePosition=1&sourceType=web_catalogue&impressionId=bce0649f-44a2-4061-88c6-6b47e9886e03&utm_source=sweatpals_web&utm_medium=web_catalogue&utm_campaign=web_catalogue",
      "contact": "@projectpevents",
      "price": "$25-35"
    },
    {
      "date": "2026-04-18",
      "time": "8:00",
      "ampm": "AM",
      "title": "Pi-Lattes On the Green",
      "location": "PopStroke",
      "description": "This isn't your typical studio Pilates class squeezed between four walls, but a full-body flow session happening outdoors on PopStroke's expansive green space where fresh air and natural light become part of your workout equation. At $28, you're getting premium instruction in a setting that makes breaking a sweat feel less like punishment and more like the kind of thoughtful self-care that actually sticks.",
      "category": "Wellness & Fitness",
      "color": "#D95D39",
      "bookingUrl": "https://www.eventbrite.com/e/pilattes-on-the-green-tickets-1986488574802?utm_experiment=test_share_listing&aff=ebdsshios&sg=572a89a94a1cee13bc3b3e29d8a62ac6ec4b1bb76a9c8455f53214c691ebb564d639b3c9c2e7b443824e4804b23544d0c014751f37ae4d1794f51a543e30fc52c5ec5ebb3fc78b9de1d8b57ace",
      "contact": "@pilatteslv",
      "price": 28
    },
    {
      "date": "2026-04-19",
      "time": "13:00",
      "ampm": "PM",
      "title": "Chair Fitness with The Overcoming Warriors Club",
      "location": "Sheree Michelle Fitness Studio",
      "description": "Join The Overcoming Warriors Club for an empowering chair fitness session that proves movement is for every body, regardless of mobility or fitness level. This inclusive workout at Sheree Michelle Fitness Studio creates a supportive community where strength meets accessibility, and you'll leave feeling accomplished and energized.",
      "category": "Wellness & Fitness",
      "color": "#D95D39",
      "bookingUrl": "https://files.bizlyapp.com/widget/form/RTAgRyr9nrBEbaFjydD2?notrack=true&utm_source=linktree_profile_share&utm_medium=social&utm_content=link_in_bio&fbclid=PAdGRleAQprcNleHRuA2FlbQIxMQBzcnRjBmFwcF9pZA8xMjQwMjQ1NzQyODc0MTQAAaeSLMtl6X56vfj5YfDS4wTOXAEGiVWVOApLoZuskcQOHSH7yyXhAgLnmC7hQA_aem_Xy1aqBQNkAqYWMHxAtGPvA",
      "contact": "@theovercomingwarriorsclub",
      "price": 18
    },
    {
      "date": "2026-04-19",
      "time": "16:00",
      "ampm": "PM",
      "title": "Yoga In the Park",
      "location": "Flamingo Park",
      "description": "Join Solely Committed Co. for a evening session of yoga in the park. Each session is community offerings and donations are accepted. Please reach out to @breathewithraven for any additional information.",
      "category": "Wellness & Fitness",
      "color": "#D95D39",
      "bookingUrl": "",
      "contact": "@breathewithraven",
      "price": "Free"
    },
    {
      "date": "2026-04-19",
      "time": "14:15",
      "ampm": "PM",
      "title": "Pilates and Praise",
      "location": "Sunset Park",
      "description": "There's something absolutely magical about combining mindful movement with uplifting music as the sun sets over the park, and this unique fusion class delivers exactly that soul-nourishing experience you've been craving. Trust me when I say this isn't your typical workout. It's a beautiful blend of Pilates flow and faith based vibes that will leave you feeling both physically strengthened and spiritually renewed.",
      "category": "Wellness & Fitness",
      "color": "#D95D39",
      "bookingUrl": "https://www.eventbrite.com/e/pilates-and-praise-tickets-1985013444648?aff=eprofsaved",
      "contact": "@inthevinelv",
      "price": 12
    },
    {
      "date": "2026-04-19",
      "time": "23:00",
      "ampm": "PM",
      "title": "Paws & Pause: Puppy Yoga",
      "location": "Luxe Linx Permanent Jewlery",
      "description": "The fact that this puppy yoga session happens inside a permanent jewelry studio means you're practicing downward dog while surrounded by delicate gold chains and sparkling ear cuffs, creating an unexpectedly luxe backdrop for your wellness hour. At $20, it's the kind of perfectly weird Las Vegas experience that somehow makes complete sense once you're there, stretching alongside adorable puppies in between display cases of dainty body jewelry.",
      "category": "Wellness & Fitness",
      "color": "#D95D39",
      "bookingUrl": "https://sweatpals.com/event/paws-pause/2026-04-19?sourceCollectionPosition=2&sourceCollection=trending&sourcePosition=2&sourceType=web_catalogue&impressionId=bce0649f-44a2-4061-88c6-6b47e9886e03&utm_source=sweatpals_web&utm_medium=web_catalogue&utm_campaign=web_catalogue",
      "contact": "@luxeera.co",
      "price": 20
    },
    {
      "date": "2026-04-19",
      "time": "16:30",
      "ampm": "PM",
      "title": "Vegas Latinas: Makeup y Mas",
      "location": "St. Felix Sin City",
      "description": "You know that feeling when you discover a hidden gem that perfectly blends beauty, culture, and community? This intimate workshop celebrates Latina beauty traditions while teaching you insider makeup techniques that will have everyone asking who did your look.",
      "category": "Creative Workshop",
      "color": "#4A4E69",
      "bookingUrl": "https://www.tixtree.com/e/makeup-y-mas-acd48fea5556?utm_source=ig&utm_medium=social&utm_content=link_in_bio&fbclid=PAZnRzaAREsjhleHRuA2FlbQIxMQBzcnRjBmFwcF9pZA8xMjQwMjQ1NzQyODc0MTQAAadttaOhJKtsxahRHyTv8Z-tQICQ0H6MnprLg4-RhLaq4goA6gGTtroS6t970g_aem_UHF7FdIX24IhC_hmU2XBeg",
      "contact": "@vegaslatinas",
      "price": 15
    },
    {
      "date": "2026-04-19",
      "time": "11:00",
      "ampm": "AM",
      "title": "Mami Pilates Club: Pilates & Perro/Dalee",
      "location": "Rhythms Dance Studio",
      "description": "This is the fusion class you didn't know you needed—combining the core-strengthening power of Pilates with the rhythmic energy of perreo and dalee for a workout that's equal parts sculpting and celebration. Trust me, you'll leave class feeling stronger, more confident, and with moves that'll have everyone asking where you learned to flow like that.",
      "category": "Wellness & Fitness",
      "color": "#D95D39",
      "bookingUrl": "https://www.tixtree.com/e/pilates-perreo-dalee-3d0242ae3d6b?utm_source=ig&utm_medium=social&utm_content=link_in_bio&fbclid=PAZnRzaAREtAhleHRuA2FlbQIxMQBzcnRjBmFwcF9pZA8xMjQwMjQ1NzQyODc0MTQAAadw-vD2yIlvbXkg-1FLrg9LuEBXiZg9rhDL6WKdbEZnkHs2wbFO4K7knXIcmw_aem_NzT5RS9WmVij6X63GpCNUg",
      "contact": "@mamipilatesclub",
      "price": 32
    },
    {
      "date": "2026-04-19",
      "time": "8:00",
      "ampm": "AM",
      "title": "Poses For Paws",
      "location": "UnCommons PS3 Rooftop, 6880 Helen Toland Street Las Vegas, NV 89113",
      "description": "Join this heartwarming morning of yoga, music, and community where every stretch makes a difference - 100% of proceeds support local animal rescue while you flow with purpose on a stunning Vegas rooftop. This is where wellness meets compassion, complete with adoptable pups, raffles, and the kind of meaningful connections that make Sunday mornings unforgettable.",
      "category": "Wellness & Fitness",
      "color": "#D95D39",
      "bookingUrl": "https://www.eventbrite.com/e/poses-for-paws-tickets-1984913939024?utm_source=ig&utm_medium=social&utm_content=link_in_bio&fbclid=PAZnRzaAREthFleHRuA2FlbQIxMQBzcnRjBmFwcF9pZA8xMjQwMjQ1NzQyODc0MTQAAaceG1d-hbB9daRTof2ce8mseOB69CcA7HzDD09KUsd5U5oiIBN-vMTWrQW3wg_aem_VGm6RI2Fhe3BsuN8kB1zeA",
      "contact": "@yogaforlifelv",
      "price": 12.5
    },
    {
      "date": "2026-04-23",
      "time": "18:00",
      "ampm": "PM",
      "title": "Spring, Coloring, Chisme",
      "location": "Velvet Vine Wine",
      "description": "Embrace the season's creative energy at this perfectly curated blend of artistic expression and delightful conversation over cafecito. This intimate gathering at Velvet Vine Wine offers the ideal excuse to slow down, color outside the lines, and connect with like-minded souls who appreciate life's beautiful, simple pleasures.",
      "category": "Creative Workshop",
      "color": "#4A4E69",
      "bookingUrl": "https://posh.vip/e/spring-coloring-chisme-?utm_source=ig&utm_medium=social&utm_content=link_in_bio&fbclid=PAZnRzaAREsdlleHRuA2FlbQIxMQBzcnRjBmFwcF9pZA8xMjQwMjQ1NzQyODc0MTQAAafOYSKNOhKgN9IRor0Q9h7YFKx-_Y_F88fr6z_tt3j0n4N-xC7vwEOdH8Cfrw_aem_O2vPtMLUOUH-T6pOkAyrtQ",
      "contact": "@cafecitoychisme",
      "price": 15
    },
    {
      "date": "2026-04-24",
      "time": "18:30",
      "ampm": "PM",
      "title": "Courtyard Cinema - Devil Wears Prada",
      "location": "1230 S Casino Center Blvd",
      "description": "Step into an enchanting evening of cinema magic with this intimate outdoor screening of The Devil Wears Prada, complete with cozy pajama party vibes, games, and all the movie night essentials under the stars. This is your chance to live out your main character dreams in a curated, female-focused experience that perfectly blends comfort with style in Vegas's Arts District.",
      "category": "Music & Entertainment",
      "color": "#7B3E19",
      "bookingUrl": "https://www.vegas4her.com/bougie-bingo-2?utm_source=ig&utm_medium=social&utm_content=link_in_bio&fbclid=PAZnRzaAREtadleHRuA2FlbQIxMQBzcnRjBmFwcF9pZA8xMjQwMjQ1NzQyODc0MTQAAaeN6vIK3rJb4OicLN1m_TBvDFgGPaBj7OYB5xkjnb-bhQGVIj-mzCqBwlKcrQ_aem_GvmGhtCVao2iIjO-m8Q8Kg",
      "contact": "@vegas4her",
      "price": 25
    },
    {
      "date": "2026-04-24",
      "time": "19:00",
      "ampm": "PM",
      "title": "Wine & Wicks at Velvet Vine Wine",
      "location": "511 S Las Vegas Blvd Las Vegas, NV 89101 United States",
      "description": "You'll want to clear your calendar for this divine pairing of premium wines and hands-on candle crafting at one of Vegas's most intimate wine destinations. Picture yourself sipping carefully curated vintages while learning the art of creating custom scented candles—it's the perfect blend of relaxation and creativity that'll leave you with both a beautiful handmade piece and memories worth savoring.",
      "category": "Creative Workshop",
      "color": "#4A4E69",
      "bookingUrl": "https://handmadepiecesofluv.com/products/candle-making-experience-velvet-vine?utm_source=ig&utm_medium=social&utm_content=link_in_bio&fbclid=PAZnRzaARP9NRleHRuA2FlbQIxMQBzcnRjBmFwcF9pZA8xMjQwMjQ1NzQyODc0MTQAAadKX3w0_eH0jVy9kOJ0UEuNPTGSM5fJNiZ83INT2yU9PYcAOfluEteI4fOj8Q_aem_2rBOdjZ0AK7egwbtsj-_hQ",
      "contact": "@piecesofluvcandles",
      "price": 45
    },
    {
      "date": "2026-04-24",
      "time": "16:30",
      "ampm": "PM",
      "title": "Babes,Bites and Blankets",
      "location": "2601 E Sunset Rd",
      "description": "Join this girls' picnic day for an afternoon of connection, delicious bites, and cozy vibes that promises to be the perfect blend of relaxation and socializing. This intimate gathering is curated for those in the know, offering a beautiful opportunity to meet like-minded women in a charming outdoor setting.",
      "category": "Social",
      "color": "#D95D39",
      "bookingUrl": "https://partiful.com/e/BAl2qJoohmWDxpx5jTHa?utm_source=ig&utm_medium=social&utm_content=link_in_bio&fbclid=PAZnRzaART70ZleHRuA2FlbQIxMQBzcnRjBmFwcF9pZA8xMjQwMjQ1NzQyODc0MTQAAad3bl_cgOIaC6vrfPSC5GC6Qa1osV-Vb0C15I5RU-cQzz3QNWY-mfP5XFh2Lw_aem_hqn3oQQfcx_hF1XtL7tXBw",
      "contact": "@thebabeclublv",
      "price": "Free"
    },
    {
      "date": "2026-04-25",
      "time": "16:00",
      "ampm": "PM",
      "title": "Aprende Conmigo: The Matcha Experience",
      "location": "Take It Easy Roasters",
      "description": "Dive deep into the ancient art of matcha with this immersive experience that'll have you whisking like a true tea ceremony master in no time. This is your chance to discover the meditative ritual behind every perfect cup while connecting with fellow wellness enthusiasts who appreciate life's most refined pleasures.",
      "category": "Food & Drink",
      "color": "#7B3E19",
      "bookingUrl": "https://posh.vip/e/aprende-conmigothe-matcha-experience",
      "contact": "@amigamovement",
      "price": 50
    },
    {
      "date": "2026-04-25",
      "time": "18:00",
      "ampm": "PM",
      "title": "The Calatina Wine Mixer",
      "location": "Vegas Valley Winery",
      "description": "This exclusive wine experience brings together Vegas's most discerning palates for an evening of exceptional vintages and elevated company. It's the kind of intimate gathering where meaningful connections are made over perfectly curated selections - exactly what our sophisticated community craves.",
      "category": "Food & Drink",
      "color": "#7B3E19",
      "bookingUrl": "https://www.eventbrite.com/e/the-catalina-wine-mixer-tickets-1985926767421?utm-medium=discovery&utm-campaign=social&utm-content=attendeeshare&utm-source=up&utm-term=user-profile&aff=ebdsshcopyurl",
      "contact": "@vegasvalleywinery",
      "price": 40
    },
    {
      "date": "2026-04-25",
      "time": "14:00",
      "ampm": "PM",
      "title": "Pilatesland with Core & Pour Social Club",
      "location": "Pilatesland",
      "description": "If you're the type who treats your body like the temple it is but knows that breaking a sweat should come with good company and even better energy, this is your Saturday morning salvation. You'll get that deep burn that makes you feel alive, then stick around to connect with women who understand that wellness isn't just about the workout — it's about building a life that feels as strong as you are.",
      "category": "Wellness & Fitness",
      "color": "#D95D39",
      "bookingUrl": "https://app.glofox.com/portal/?utm_source=ig&utm_medium=social&utm_content=link_in_bio&fbclid=PAdGRleAQ7uxxleHRuA2FlbQIxMQBzcnRjBmFwcF9pZA8xMjQwMjQ1NzQyODc0MTQAAafRuDa9tq6EjBpDJF7NvngEqfNjixNxIqN7yjdS8vggjH7RCRQhk7BGReitsA_aem_UXNed8KG5M6ZfNMHHQ97Fw#/branch/68642e2c54d502c0cd03d1e1/courses",
      "contact": "@coreandpoursocialclub",
      "price": "Free"
    },
    {
      "date": "2026-04-25",
      "time": "11:00",
      "ampm": "AM",
      "title": "The Overcoming Warriors Club: Create Bubble Bars",
      "location": "Honey Vintage and Bath, 231 W Charleston Blvd suite 140, Las Vegas, NV, USA",
      "description": "Join the Overcoming Warriors Club at Honey Vintage and Bath for an empowering afternoon where you'll craft luxurious bubble bars while connecting with an incredible community of resilient women. This isn't just about creating beautiful bath products, it's about celebrating your strength, sharing stories, and leaving with both handmade treasures and newfound friendships that'll remind you how powerful you truly are.",
      "category": "Creative Workshop",
      "color": "#4A4E69",
      "bookingUrl": "https://honeyvintageandbath.com/ola/services/the-overcoming-warriors-club-create-bubble-bars-april-25-2026?utm_source=linktree_profile_share&utm_medium=social&utm_content=link_in_bio&fbclid=PAZnRzaAREsRBleHRuA2FlbQIxMQBzcnRjBmFwcF9pZA8xMjQwMjQ1NzQyODc0MTQAAadpqCjjtUFyb32pmYbgD0Ytj0uBLWBX4wtf4EtMNopvp3mmWFhTmecRVKEaPw_aem_275owTG4Ree3gtN2uV2bXg",
      "contact": "@theovercomingwarriorsclub",
      "price": 27
    },
    {
      "date": "2026-04-25",
      "time": "18:00",
      "ampm": "PM",
      "title": "Junk Journal Club(Western Themed)",
      "location": "Container Park",
      "description": "Channel your inner cowgirl at this delightfully nostalgic crafting session where you'll create a beautifully weathered journal filled with vintage ephemera, pressed flowers, and all those dreamy western-inspired touches that make your heart sing. Trust me, this is the perfect excuse to slow down, get your hands dirty with some serious creative magic, and leave with a one-of-a-kind keepsake that captures the free-spirited energy we're all craving.",
      "category": "Creative Workshop",
      "color": "#4A4E69",
      "bookingUrl": "https://www.shopmamasage.com/?utm_source=ig&utm_medium=social&utm_content=link_in_bio&fbclid=PAZnRzaARP9EpleHRuA2FlbQIxMQBzcnRjBmFwcF9pZA8xMjQwMjQ1NzQyODc0MTQAAafhHN8JDEUepTgN2W_kflTC3evPg3lj8Xxcru7rQApJHv31HKDEamR8qmyWPg_aem_q6OWV_GuUL-eU4VtEndEkQ",
      "contact": "@junkjournalclublasvegas",
      "price": 30
    },
    {
      "date": "2026-04-25",
      "time": "8:00",
      "ampm": "AM",
      "title": "Pilates at the ranch",
      "location": "TBD",
      "description": "There's something absolutely magical about taking your Pilates practice outdoors, especially when it's set against the stunning backdrop of a working ranch where fresh air and natural beauty become part of your workout. This is the kind of experience that will have you feeling both grounded and elevated.",
      "category": "Wellness & Fitness",
      "color": "#D95D39",
      "bookingUrl": "https://www.eventbrite.com/e/pilates-at-the-ranch-tickets-1987831566727?aff=oddtdtcreator&keep_tld=true&utm_source=ig&utm_medium=social&utm_content=link_in_bio&fbclid=PAZnRzaART8MFleHRuA2FlbQIxMQBzcnRjBmFwcF9pZA8xMjQwMjQ1NzQyODc0MTQAAacwymAxXlraUIrradbdhRYuXT3qt6S7knoO58GoXuxES1x126BcsJGK1L7Kag_aem_Rga-I6HuoqgzUjHL1t9n0Q",
      "contact": "@pilatesattheranch",
      "price": 23
    },
    {
      "date": "2026-04-26",
      "time": "9:30",
      "ampm": "AM",
      "title": "Driven & Defined: A Land Rover x TruFusion Pilates Experience",
      "location": "Land Rover Las Vegas",
      "description": "This is an exclusive Pilates session that perfectly marries luxury automotive elegance with mindful movement, hosted in the sleek showroom of Land Rover Las Vegas where you'll flow alongside their stunning vehicles. This isn't just any wellness class—it's a curated experience where TruFusion's expert instructors guide you through a rejuvenating practice that embodies the same precision and strength as the iconic cars surrounding you.",
      "category": "Wellness & Fitness",
      "color": "#D95D39",
      "bookingUrl": "https://www.eventbrite.com/e/driven-defined-a-land-rover-x-trufusion-pilates-experience-tickets-1985462764576?aff=eprofsaved",
      "contact": "@vegasgirlevents",
      "price": "$50-60"
    },
    {
      "date": "2026-04-26",
      "time": "17:30",
      "ampm": "PM",
      "title": "Houseplant Bingo",
      "location": "Fergusons's Downtown",
      "description": "This delightfully quirky plant-themed bingo experience is exactly the kind of unexpected Vegas gem that locals love to discover - where your green thumb meets good vibes in the most entertaining way possible. It's the perfect blend of community connection and botanical knowledge that'll have you seeing the city's creative side beyond the Strip.",
      "category": "Social",
      "color": "#D95D39",
      "bookingUrl": "https://lvplantcollective.com/products/houseplant-bingo",
      "contact": "@lvplantcollective",
      "price": 45
    },
    {
      "date": "2026-04-26",
      "time": "14:00",
      "ampm": "PM",
      "title": "The Lip Lab : MAC Cosmetics X Spa Girl In the City Experience",
      "location": "MAC Cosmetics @ Dillard's Downtown Summerlin, 1980 Festival Plaza Drive Las Vegas, NV 89135",
      "description": "Discover your signature lip shade at this intimate MAC Cosmetics experience where you'll test personalized shades, work with professional artists, and sip champagne while learning what truly complements your skin tone. With only 30 spots available, this curated beauty lab includes professional application, a photobooth moment, charcuterie, and an exclusive gift bag—plus the chance to get $25 back when you purchase $100 in products.",
      "category": "Creative Workshop",
      "color": "#4A4E69",
      "bookingUrl": "https://www.eventbrite.com/e/the-lip-lab-mac-cosmetics-x-spa-girl-in-the-city-experience-tickets-1986514929630?aff=oddtdtcreator&utm_source=ig&utm_medium=social&utm_content=link_in_bio&fbclid=PAZnRzaAREs0xleHRuA2FlbQIxMQBzcnRjBmFwcF9pZA8xMjQwMjQ1NzQyODc0MTQAAacfy8ev5oBUEcb1JpK-MRoJxhJVDTAMnTtUA5UnU1kX_7JqrYRmudp3AhYVjg_aem_7KyOf6YvvZoYD9pXCdBH5A",
      "contact": "@spagirlinthecity",
      "price": 35
    },
    {
      "date": "2026-04-26",
      "time": "9:00",
      "ampm": "AM",
      "title": "Slow Sundays Club LV — Gentle Yoga + JoJo Cafe",
      "location": "To be announced",
      "description": "This intimate Sunday morning ritual combines gentle yoga flows with exclusive JoJo Cafe tastings, creating the perfect antidote to Vegas's high-energy scene. It's the kind of hidden gem where you'll find yourself surrounded by like-minded souls seeking a softer, more intentional start to their week.",
      "category": "Wellness & Fitness",
      "color": "#D95D39",
      "bookingUrl": "https://www.eventbrite.com/e/slow-sundays-club-lv-gentle-yoga-jojo-cafe-tickets-1986915005267?utm_experiment=test_share_listing&aff=ebdsshios&sg=02b6656d3a799a0b8c5fdc118777b504982f3b047c2380a2bbae43509eb0d63c6083fd38ede43ec4f5d943862f59dcd11d8e9ee1124d2c5ab53aff01214aecc0ecd1dab9f13d6ae6cda83ffd4b",
      "contact": "@slowsundayslv",
      "price": 27
    },
    {
      "date": "2026-04-26",
      "time": "10:00",
      "ampm": "AM",
      "title": "Flowers & Friends: Pot Painting",
      "location": "Springs Cafe at the Springs Preserve, 333 S Valley View Blvd, Las Vegas, NV",
      "description": "This adorable spring DIY experience lets you paint your own terracotta flower pot while connecting with like-minded women in an air-conditioned oasis before Vegas summer hits. You'll leave with your custom creation plus soil and seeds to start your own plant baby – it's the perfect blend of creativity, community, and springtime magic that the coolest girls are already talking about.",
      "category": "Creative Workshop",
      "color": "#4A4E69",
      "bookingUrl": "https://partiful.com/e/Y8Qr60i6tQppfh0Ubvju?utm_source=ig&utm_medium=social&utm_content=link_in_bio&fbclid=PAZnRzaARP9VpleHRuA2FlbQIxMQBzcnRjBmFwcF9pZA8xMjQwMjQ1NzQyODc0MTQAAaf3A-kcdwPUMNQITzrULsgDvQ31aMHMFSOk68Xyt_bmlR3eyn7m6HEMiVowBA_aem_hS7JgVi5UOZaAUFJNLzdDw",
      "contact": "@cozycollectivelv",
      "price": "$15 per person"
    },
    {
      "date": "2026-04-27",
      "time": "18:00",
      "ampm": "PM",
      "title": "Sunset Yoga in the Park🌱",
      "location": "9275 S Buffalo Dr, Las Vegas, NV 89178, USA",
      "description": "There's something absolutely magical about practicing yoga as the desert sky transforms into a canvas of amber and rose, and this outdoor session captures that perfect Vegas golden hour energy we're always chasing. You'll leave feeling both grounded and glowing, with that serene post-flow radiance that only comes from moving your body in nature's most photogenic lighting.",
      "category": "Wellness & Fitness",
      "color": "#D95D39",
      "bookingUrl": "https://sweatpals.com/event/sunset-yoga-in-the-park-99fd?utm_source=user_share_5e649ed6-5bf9-4e15-9251-25f076a61ade&utm_medium=shared_link&utm_campaign=event_share&utm_content=link_in_bio&fbclid=PAZnRzaARE_FlleHRuA2FlbQIxMQBzcnRjBmFwcF9pZA8xMjQwMjQ1NzQyODc0MTQAAae90GpfepHb8l9T2yYD4BXJgtXQBEE7Tb0rVus96d-asoNPhlHquCMtH5eNJg_aem_r236VlUXgHyhgyANoVxusg",
      "contact": "@yinstantblissyoga",
      "price": 15
    },
    {
      "date": "2026-04-27",
      "time": "18:00",
      "ampm": "PM",
      "title": "Neurospicy Pickleball Social",
      "location": "RSVP for location",
      "description": "This isn't your typical pickleball game—it's a celebration of neurodivergent minds coming together for some friendly competition and genuine connection on the court. You'll find yourself among a wonderfully diverse group of players who get that sometimes the best conversations happen between serves, and every swing is a chance to be authentically you.",
      "category": "Wellness & Fitness",
      "color": "#D95D39",
      "bookingUrl": "https://partiful.com/e/f0KYnPqlIpHfQrgjaKHL?utm_source=ig&utm_medium=social&utm_content=link_in_bio&fbclid=PAZnRzaARP82lleHRuA2FlbQIxMQBzcnRjBmFwcF9pZA8xMjQwMjQ1NzQyODc0MTQAAaeBZSCXcRxK9meT_XoHhH1CG0BFtojPaJ-0PiFKkfubfL9VLs9qLm1Zn_E6gg_aem_XWjCD7gUnWXRMBOCMK_cgg",
      "contact": "@thesoulsparklv",
      "price": "$6-$12"
    },
    {
      "date": "2026-04-30",
      "time": "18:00",
      "ampm": "PM",
      "title": "Manos y Masa: Papusa Making Workshop with Vegas Latinas",
      "location": "Voodoo Brewery",
      "description": "Get ready to roll up your sleeves and dive into the art of authentic pupusa making alongside the incredible community at Vegas Latinas, where you'll learn traditional techniques passed down through generations. This hands-on experience at Voodoo Brewery combines the best of cultural connection, delicious homemade comfort food, and the kind of evening that feeds both your soul and your Instagram feed.",
      "category": "Food & Drink",
      "color": "#7B3E19",
      "bookingUrl": "https://www.tixtree.com/e/manos-y-masa-for-everyone-a4e6202b4deb?utm_source=ig&utm_medium=social&utm_content=link_in_bio&fbclid=PAZnRzaART7g1leHRuA2FlbQIxMQBzcnRjBmFwcF9pZA8xMjQwMjQ1NzQyODc0MTQAAafCUrnR90wSjL4fSW16RMpEyQrY9PO2-HJ17VT5k1Zj_2IWbYKV2wVl7AmnBQ_aem_W4oV16bwGIReqjSvcCtjRg",
      "contact": "@vegaslatinas",
      "price": 39
    },
    {
      "date": "2026-05-02",
      "time": "9:00",
      "ampm": "AM",
      "title": "Horses X Pilates",
      "location": "1937 Calico Dr",
      "description": "Elevated morning combining horses and Pilates movement.",
      "category": "Fitness & Wellness",
      "color": "#D95D39",
      "bookingUrl": "lwactive.com",
      "contact": "@lwactive",
      "price": 85
    },
    {
      "date": "2026-05-02",
      "time": "19:00",
      "ampm": "PM",
      "title": "New Vista Wine Walk at Downtown Summerlin",
      "location": "Downtown Summerlin, 1825 Festival Plaza Drive, Las Vegas, NV 89135",
      "description": "This beloved Las Vegas tradition since 2004 offers the perfect sophisticated evening out with 18+ wine tasting stations while supporting an incredible local cause that's been empowering people with intellectual and developmental disabilities for 40 years. With souvenir glassware, premium VIP tastings, and even dog-friendly vibes, it's the kind of meaningful social experience that lets you sip, stroll, and make a real difference in your community.",
      "category": "Food & Drink",
      "color": "#7B3E19",
      "bookingUrl": "https://www.eventbrite.com/e/new-vista-wine-walk-at-downtown-summerlin-tickets-1981259288867?aff=ebdssbcategorybrowse",
      "contact": "@newvistanv",
      "price": "$50 -110"
    },
    {
      "date": "2026-05-02",
      "time": "17:00",
      "ampm": "PM",
      "title": "Rooftop Ride: Under The Lights",
      "location": "BLVD Las Vegas",
      "description": "Get ready to elevate your fitness game with this exclusive rooftop cycling experience that combines stunning city views with an invigorating workout under the evening lights. This is the kind of insider fitness event that will have you feeling like you've discovered the city's best-kept wellness secret.",
      "category": "Wellness & Fitness",
      "color": "#D95D39",
      "bookingUrl": "https://www.ethoclub.com/events/rooftop-ride-under-the-lights?utm_source=ig&utm_medium=social&utm_content=link_in_bio&fbclid=PAZnRzaARE_AVleHRuA2FlbQIxMQBzcnRjBmFwcF9pZA8xMjQwMjQ1NzQyODc0MTQAAacL6gOGi426h0jMNCzZpOrhxscL8Rgrm-_yZWtFxSK4Mp1oN8UVUUhxrpbRjg_aem_SOvMY42l3wG-QeiISP22ww",
      "contact": "@ethoclub",
      "price": 49
    },
    {
      "date": "2026-05-03",
      "time": "13:00",
      "ampm": "PM",
      "title": "Vlasic Vinyasa",
      "location": "NuWu Courtyard, 1235 Paiute Cir",
      "description": "The page content appears to require JavaScript to load properly, so I cannot extract any event details from the information provided. Unfortunately, I'm unable to create a meaningful description without access to the actual event details.",
      "category": "Wellness & Fitness",
      "color": "#D95D39",
      "bookingUrl": "https://eventhi.io/events/vlasic-vinyasa-with-dejha-mae-14138?fbclid=PARlRTSAREtp9leHRuA2FlbQIxMABzcnRjBmFwcF9pZA8xMjQwMjQ1NzQyODc0MTQAAae04BHEFDNv-jJzW5-tttgtfEulRgOydqoxaRKh1pdfUM_Yt-V7aQhsSwyi7A_aem_HY4BtLynoWVc4b9kNSXmRA",
      "contact": "@vlasiclabs",
      "price": 15
    },
    {
      "date": "2026-05-03",
      "time": "14:00",
      "ampm": "PM",
      "title": "Cinco de Mayo Glute Pilates + Perreo",
      "location": "Ilumina on Raiders Way",
      "description": "Get ready to spice up your Sunday and celebrate Cinco de Mayo with this brilliant fusion of targeted glute work and reggaeton rhythms that'll have you feeling strong.",
      "category": "Wellness & Fitness",
      "color": "#D95D39",
      "bookingUrl": "https://www.tixtree.com/e/cinco-de-mayo-glute-pilates-perreo-fbb9f857653e?utm_source=ig&utm_medium=social&utm_content=link_in_bio&fbclid=PAZnRzaART631leHRuA2FlbQIxMQBzcnRjBmFwcF9pZA8xMjQwMjQ1NzQyODc0MTQAAaeMwXwSv7FBWgL5C5m84ypPCGNtHFqbLjKU44U0WoTxpaTUrAUjHHoN_C7VEw_aem_sWeiPszONG5dP838rLRlNQ",
      "contact": "@mamipilattesclub",
      "price": 32
    },
    {
      "date": "2026-05-09",
      "time": "10:00",
      "ampm": "AM",
      "title": "Mothers Day at The Ranch",
      "location": "4975 N Miller Ln Las Vegas, NV 89149, USA",
      "description": "This heartwarming Mother's Day celebration at a local ranch offers the perfect blend of relaxation and family fun, with complimentary chair massages for the first 25 moms, unlimited animal cuddles, and special craft activities. It's an insider's gem where military families get discounted rates and everyone can experience the therapeutic joy of connecting with horses and farm animals in a beautiful ranch setting.",
      "category": "Family Friendly",
      "color": "#4A4E69",
      "bookingUrl": "https://www.zeffy.com/en-US/ticketing/mothers-day-at-the-ranch?fbclid=PARlRTSARE-iBleHRuA2FlbQIxMQBzcnRjBmFwcF9pZA8xMjQwMjQ1NzQyODc0MTQAAafT4YWsCsQFOf1T7O-M1qVt1QGtxgo_3AAV44hGmtKWqKPibl5kqKsZP2eqJQ_aem_9McBzsD1pPPx5TnOEYYo9Q",
      "contact": "@horses4heroeslv",
      "price": "Free for Mothers and Grandmothers, $10-15 for children"
    },
    {
      "date": "2026-05-10",
      "time": "14:00",
      "ampm": "PM",
      "title": "Perfume & Pastries Event",
      "location": "Bottega Exchange | 6675 S Tenaya Way #200 Las Vegas, NV 89113",
      "description": "This enchanting experience combines the best of both worlds - indulgent pastry tastings and the artistry of crafting your own signature 30mL fragrance inspired by gourmet delights. Guided by expert perfumers in an intimate setting, you'll create a custom scent and take home a luxurious premium fragrance bottle with personalized souvenir label as the perfect keepsake from this celebration of creativity and motherhood.",
      "category": "Creative Workshop",
      "color": "#4A4E69",
      "bookingUrl": "https://www.thediyfragrancebar.com/shop/p/4o40qsy0h6hx64biqvzy8arvrk0my0?fbclid=PARlRTSAREtSlleHRuA2FlbQIxMABzcnRjBmFwcF9pZA8xMjQwMjQ1NzQyODc0MTQAAadrSdxSbMs1SXNi52Vy8_KOMe7o5IZoekX73HzO0k-JLm5nkCrIejSWqBE-zg_aem_gHQHczvc3vJgdvfeo6APqA",
      "contact": "@thediyfragrancebar_",
      "price": "from $150.00"
    },
    {
      "date": "2026-05-16",
      "time": "14:00",
      "ampm": "PM",
      "title": "Model x Runway Class with Miss Arizona",
      "location": "To be announced",
      "description": "Step into the modeling world with this exclusive runway masterclass led by Miss Arizona USA 2025, where you'll learn industry fundamentals and perfect your catwalk technique. This insider experience covers everything from agency expectations to heel techniques, giving you the professional edge you need to strut with confidence.",
      "category": "Creative Workshop",
      "color": "#4A4E69",
      "bookingUrl": "https://www.eventbrite.com/e/model-x-runway-class-with-miss-arizona-tickets-1987687846857?aff=oddtdtcreator&utm_source=ig&utm_medium=social&utm_content=link_in_bio&fbclid=PAZnRzaART7upleHRuA2FlbQIxMQBzcnRjBmFwcF9pZA8xMjQwMjQ1NzQyODc0MTQAAaee4TEF7SmSut9VCosM58vco2W1rH74uSSri2bwhvACyozxwFEOeFb1HGD2ng_aem_WYACk7nsn2ZfteWmgqhPiA",
      "contact": "@_puzzledsociety_",
      "price": 55
    },
    {
      "date": "2026-10-09",
      "time": "--",
      "ampm": "--",
      "title": "Las Vegas Black Rodeo",
      "location": "Horseman’s Park",
      "description": "The Hottest Shows on Dirt featuring the 2026 Black Rodeo USA season.",
      "category": "Social & Culture",
      "color": "#4A4E69",
      "bookingUrl": "blackrodeousa.com",
      "contact": ""
    }
  ],
  "recurring": [
    {
      "days": "Mondays",
      "time": "6-7pm",
      "title": "Mat Mondays: Pilates with Music Box Movement",
      "location": "Sheree Michelle Fitness Studio",
      "description": "",
      "price": "24",
      "category": "Fitness & Wellness",
      "bookingUrl": "https://sweatpals.com/event/mat-mondays-rhythm-roots-fb11f3/2026-04-06"
    },
    {
      "days": "Thursdays & Saturdays",
      "time": "6:30-8:30pm(Thursdays) 9:30am-12:30pm(Saturdays)",
      "title": "Beginner Archery & Lesson",
      "location": "Clark County Shooting Complex",
      "description": "",
      "price": "15",
      "category": "Fitness & Wellness",
      "bookingUrl": ""
    },
    {
      "days": "Wednesdays",
      "time": "6-7pm",
      "title": "Uncommons Unwind: Free Rooftop Pilates hosted by The Good Place",
      "location": "Uncommons (Parking Structure 3 Rooftop)",
      "description": "",
      "price": "Free",
      "category": "Fitness & Wellness",
      "bookingUrl": ""
    },
    {
      "days": "Tuesdays, Thursdays, & Saturdays",
      "time": "9-10am",
      "title": "Fit4Mom Stroller Strides",
      "location": "The District at Green Valley Ranch",
      "description": "",
      "price": "",
      "category": "Fitness & Wellness",
      "bookingUrl": "https://shopthedistrictgvr.com/events/the-district-at-green-valley-ranch-fit4mom-stroller-strides-82073805-a59f-4ca0-ad44-3976df74792f"
    },
    {
      "days": "Sundays",
      "time": "10-11am",
      "title": "Fitness on the Green at GVR",
      "location": "The District at Green Valley Ranch",
      "description": "",
      "price": "Free",
      "category": "Fitness & Wellness",
      "bookingUrl": "https://shopthedistrictgvr.com/events"
    },
    {
      "days": "Various Dates",
      "time": "6:30-9:30pm",
      "title": "Movies on the Green at GVR",
      "location": "The District at Green Valley Ranch",
      "description": "",
      "price": "Free",
      "category": "Family Friendly",
      "bookingUrl": "https://shopthedistrictgvr.com/events"
    },
    {
      "days": "Tuesday-Saturday",
      "time": "7:30pm & 8:30pm",
      "title": "Line Dance Lessons",
      "location": "Stoney's North Fourty(Santa Fe)",
      "description": "",
      "price": "Free",
      "category": "Social",
      "bookingUrl": ""
    },
    {
      "days": "Thursday-Sunday",
      "time": "7:30pm & 8:30pm",
      "title": "Line Dance Lessons",
      "location": "Stoney's Rockin Country(Town Square)",
      "description": "",
      "price": "Free",
      "category": "Social",
      "bookingUrl": ""
    },
    {
      "days": "Tuesdays",
      "time": "1899-12-31T01:00:00.000Z",
      "title": "Fitness on The Lawn",
      "location": "Downtown Summerlin",
      "description": "",
      "price": "Free",
      "category": "Fitness & Wellness",
      "bookingUrl": "https://summerlin.com/event/fitness-on-the-lawn-4/"
    }
  ],
  "happyHours": [],
  "socialClubs": []
}